<?xml version="1.0" encoding="UTF-8" standalone="no"?>
<Canvas xmlns="http://www.jgrasp.org">
  <Language>Java</Language>
  <ShowTypes>false</ShowTypes>
  <Version>2</Version>
  <Grid>
    <Snap>true</Snap>
    <Show>false</Show>
  </Grid>
  <Scope id="0">
    <Name>depthFirstSearch</Name>
    <Signature>(Ljava/lang/String;)Ljava/util/List;</Signature>
    <DeclaringType>WordSearchBoard</DeclaringType>
    <Depth>34</Depth>
  </Scope>
  <Scope id="1">
    <Name>generateAdjacentCells</Name>
    <Signature>(ILjava/lang/String;)Ljava/util/List;</Signature>
    <DeclaringType>WordSearchBoard</DeclaringType>
    <Depth>35</Depth>
  </Scope>
  <Frame>
    <Bounds>
      <AutoSize>true</AutoSize>
      <X>640</X>
      <Y>160</Y>
      <W>104</W>
      <H>66</H>
    </Bounds>
    <Viewer>
      <ScopeID>0</ScopeID>
      <Expression>`local java.util.List` neighbors</Expression>
      <ViewerClass>java__lang__Object_LinkedView</ViewerClass>
    </Viewer>
  </Frame>
  <Frame>
    <Bounds>
      <AutoSize>true</AutoSize>
      <X>1020</X>
      <Y>550</Y>
      <W>104</W>
      <H>66</H>
    </Bounds>
    <LabelLoc>
      <WO>false</WO>
    </LabelLoc>
    <Viewer>
      <ScopeID>0</ScopeID>
      <Expression>`local int` c</Expression>
      <ViewerClass>_X_ElementView</ViewerClass>
    </Viewer>
  </Frame>
  <Frame>
    <Bounds>
      <AutoSize>false</AutoSize>
      <X>728</X>
      <Y>762</Y>
      <W>800</W>
      <H>616</H>
    </Bounds>
    <PanelSize>
      <Key>_X_A_A_ToStringView0</Key>
      <Order>4</Order>
      <W>806</W>
      <H>654</H>
    </PanelSize>
    <Viewer>
      <ScopeID>0</ScopeID>
      <Expression>this.wordBoard</Expression>
      <ViewerClass>_X_A_A_ToStringView</ViewerClass>
      <ViewerData>
        <Cols>16</Cols>
      </ViewerData>
    </Viewer>
  </Frame>
  <Frame>
    <Bounds>
      <AutoSize>true</AutoSize>
      <X>530</X>
      <Y>420</Y>
      <W>279</W>
      <H>300</H>
    </Bounds>
    <Viewer>
      <ScopeID>1</ScopeID>
      <Expression>`local java.util.LinkedList` validNeighbors</Expression>
      <ViewerClass>java__lang__Object_LinkedView</ViewerClass>
    </Viewer>
  </Frame>
  <Frame>
    <Bounds>
      <AutoSize>true</AutoSize>
      <X>430</X>
      <Y>800</Y>
      <W>104</W>
      <H>66</H>
    </Bounds>
    <LabelLoc>
      <WO>false</WO>
    </LabelLoc>
    <Viewer>
      <ScopeID>1</ScopeID>
      <Expression>`local int` nY</Expression>
      <ViewerClass>_X_ElementView</ViewerClass>
    </Viewer>
  </Frame>
  <Frame>
    <Bounds>
      <AutoSize>false</AutoSize>
      <X>973</X>
      <Y>240</Y>
      <W>604</W>
      <H>506</H>
    </Bounds>
    <PanelSize>
      <Key>_X_A_A_ToStringView0</Key>
      <Order>4</Order>
      <W>610</W>
      <H>544</H>
    </PanelSize>
    <Viewer>
      <ScopeID>0</ScopeID>
      <Expression>this.markBoard</Expression>
      <ViewerClass>_X_A_A_ToStringView</ViewerClass>
    </Viewer>
  </Frame>
  <Frame>
    <Bounds>
      <AutoSize>true</AutoSize>
      <X>250</X>
      <Y>790</Y>
      <W>104</W>
      <H>66</H>
    </Bounds>
    <LabelLoc>
      <WO>false</WO>
    </LabelLoc>
    <Viewer>
      <ScopeID>1</ScopeID>
      <Expression>`local int` nX</Expression>
      <ViewerClass>_X_ElementView</ViewerClass>
    </Viewer>
  </Frame>
  <Frame>
    <Bounds>
      <AutoSize>true</AutoSize>
      <X>130</X>
      <Y>130</Y>
      <W>179</W>
      <H>226</H>
    </Bounds>
    <Viewer>
      <ScopeID>0</ScopeID>
      <Expression>`local java.util.LinkedList` stack</Expression>
      <ViewerClass>java__lang__Object_LinkedView</ViewerClass>
    </Viewer>
  </Frame>
  <Frame>
    <Bounds>
      <AutoSize>true</AutoSize>
      <X>140</X>
      <Y>840</Y>
      <W>179</W>
      <H>226</H>
    </Bounds>
    <Viewer>
      <ScopeID>0</ScopeID>
      <Expression>`local java.util.LinkedList` wordPos</Expression>
      <ViewerClass>java__lang__Object_LinkedView</ViewerClass>
    </Viewer>
  </Frame>
  <Frame>
    <Bounds>
      <AutoSize>false</AutoSize>
      <X>150</X>
      <Y>580</Y>
      <W>266</W>
      <H>108</H>
    </Bounds>
    <PanelSize>
      <Key>java__lang__String_FormattedView0</Key>
      <Order>4</Order>
      <W>272</W>
      <H>146</H>
    </PanelSize>
    <Viewer>
      <ScopeID>1</ScopeID>
      <Expression>`local java.lang.String` s</Expression>
      <ViewerClass>java__lang__String_FormattedView</ViewerClass>
    </Viewer>
  </Frame>
  <Size>
    <W>1630</W>
    <H>1581</H>
  </Size>
  <ESize>
    <W>1630</W>
    <H>1581</H>
  </ESize>
</Canvas>
